facesinthings/__init__.py
facesinthings/dataset.py
facesinthings-0.1.0.dist-info/LICENSE
facesinthings-0.1.0.dist-info/METADATA
facesinthings-0.1.0.dist-info/WHEEL
facesinthings-0.1.0.dist-info/top_level.txt
facesinthings-0.1.0.dist-info/RECORD
