Metadata-Version: 2.1
Name: facesinthings
Version: 0.1.0
Summary: A PyTorch dataset for the FacesInThings dataset
Home-page: https://github.com/mhamilton723/FacesInThings
Author: Mark Hamilton, Simon Stent, Vasha DuTell, Anne Harrington, Jennifer Corbett, Ruth Rosenholtz, William T. Freeman
Author-email: markth@mit.edu
Classifier: Programming Language :: Python :: 3
Classifier: License :: OSI Approved :: MIT License
Classifier: Operating System :: OS Independent
Requires-Python: >=3.6
License-File: LICENSE
Requires-Dist: torch (>=1.7)
Requires-Dist: torchvision (>=0.8)
Requires-Dist: pandas (>=1.1)
Requires-Dist: requests (>=2.24)
Requires-Dist: Pillow (>=8.0)
